vxutils/__init__.py
vxutils/cache.py
vxutils/context.py
vxutils/convertors.py
vxutils/decorators.py
vxutils/executor.py
vxutils/logger.py
vxutils/py.typed
vxutils/tools.py
vxutils/datamodel/__init__.py
vxutils/datamodel/adapter.py
vxutils/datamodel/core.py
vxutils/datamodel/dborm.py
vxutils-20260114.dist-info/METADATA
vxutils-20260114.dist-info/WHEEL
vxutils-20260114.dist-info/RECORD
