Metadata-Version: 2.4
Name: vxutils
Version: 20260114
Summary: A toolbox for vxquant
Author-email: libao <libao@vxquant.com>
Requires-Python: >=3.10
Requires-Dist: polars>=1.36.1
Requires-Dist: pydantic>=2.10.6
Requires-Dist: python-dateutil>=2.9.0.post0
Requires-Dist: sqlalchemy>=2.0.45
